{
  "id": "app",
  "name": "timeaccouting",
  "startScreen": "app.login",
  "screens": [
    {
      "id": "blank",
      "name": "BLANK",
      "sourceAppId": "_blank",
      "sourceScreenId": "app.blank"
    },
    {
      "id": "menu",
      "name": "menu",
      "sourceAppId": "_blank",
      "sourceScreenId": "app.menu"
    },
    {
      "id": "multiselect",
      "name": "multiselect",
      "sourceAppId": "_blank",
      "sourceScreenId": "app.multiselect"
    },
    {
      "id": "mytimetable1",
      "name": "mytimetable1",
      "sourceScreenId": "app.blank",
      "sourceAppId": "_blank",
      "model": "mytimetable"
    },
    {
      "id": "enterhourspopup",
      "name": "enterhourspopup",
      "sourceScreenId": "app.blank",
      "sourceAppId": "_blank",
      "model": "enterhourspopup"
    },
    {
      "id": "login",
      "name": "login",
      "sourceScreenId": "app.login.loginconfident",
      "sourceAppId": "universaltemplates",
      "model": "login"
    },
    {
      "id": "test",
      "name": "Test",
      "sourceScreenId": "app.tableview.tabledatacool",
      "sourceAppId": "universaltemplates",
      "model": "test"
    }
  ],
  "sourceAppId": "_blank",
  "sourceScreenId": "app"
}
